hashers_passlib/__init__.py
hashers_passlib/converters.py
hashers_passlib/tests/__init__.py
hashers_passlib/tests/settings.py
hashers_passlib/tests/tests.py
django_hashers_passlib_revived-2.0.dist-info/LICENSE
django_hashers_passlib_revived-2.0.dist-info/METADATA
django_hashers_passlib_revived-2.0.dist-info/WHEEL
django_hashers_passlib_revived-2.0.dist-info/RECORD
