Metadata-Version: 2.1
Name: django-hashers-passlib-revived
Version: 2.0
Summary: Django hashers using passlib
Home-page: https://github.com/bartTC/django-hashers-passlib-revived/
License: GNU General Public License (GPL) v3
Author: Mathias Ertl
Author-email: mati@er.tl
Requires-Python: >=3.8,<4.0
Classifier: Development Status :: 6 - Mature
Classifier: Environment :: Other Environment
Classifier: Environment :: Web Environment
Classifier: Framework :: Django
Classifier: Framework :: Django :: 3.2
Classifier: Framework :: Django :: 4.0
Classifier: Framework :: Django :: 4.1
Classifier: Framework :: Django :: 4.2
Classifier: Framework :: Django :: 5.0
Classifier: Intended Audience :: Developers
Classifier: License :: OSI Approved :: GNU General Public License v3 or later (GPLv3+)
Classifier: License :: Other/Proprietary License
Classifier: Operating System :: OS Independent
Classifier: Programming Language :: Python
Classifier: Programming Language :: Python :: 3
Classifier: Programming Language :: Python :: 3.8
Classifier: Programming Language :: Python :: 3.9
Classifier: Programming Language :: Python :: 3.10
Classifier: Programming Language :: Python :: 3.11
Classifier: Programming Language :: Python :: 3.12
Classifier: Programming Language :: Python :: 3 :: Only
Classifier: Topic :: Internet :: WWW/HTTP
Classifier: Topic :: Software Development :: Libraries :: Python Modules
Classifier: Topic :: System :: Systems Administration :: Authentication/Directory
Requires-Dist: django (>=3.2)
Requires-Dist: passlib (>=1.7)
Project-URL: Changelog, https://github.com/bartTC/django-hashers-passlib-revived/blob/main/CHANGELOG.md
Project-URL: Issues, https://github.com/bartTC/django-hashers-passlib-revived/issues
Project-URL: Source, https://github.com/bartTC/django-hashers-passlib-revived/
